kafkatos3/BaseConsumer.py
kafkatos3/Compressor.py
kafkatos3/KafkaConfluentConsumer.py
kafkatos3/KafkaPythonConsumer.py
kafkatos3/MessageArchiveKafka.py
kafkatos3/S3Uploader.py
kafkatos3/ThreadPool.py
kafkatos3/__init__.py
kafkatos3/main.py
kafkatos3/metadata.py
kafkatos3/parse.py
kafkatos3/rotate.py
kafkatos3-0.2.0.dist-info/DESCRIPTION.rst
kafkatos3-0.2.0.dist-info/METADATA
kafkatos3-0.2.0.dist-info/RECORD
kafkatos3-0.2.0.dist-info/WHEEL
kafkatos3-0.2.0.dist-info/entry_points.txt
kafkatos3-0.2.0.dist-info/metadata.json
kafkatos3-0.2.0.dist-info/top_level.txt
