Metadata-Version: 2.0
Name: kafkatos3
Version: 0.2.0
Summary: Archive kafka messages to S3
Home-page: https://github.com/ConnectedHomes/kafkatos3
Author: Ben Corlett
Author-email: ben.corlett@bgch.co.uk
License: UNKNOWN
Platform: UNKNOWN
Classifier: Development Status :: 1 - Planning
Classifier: Environment :: Console
Classifier: Intended Audience :: Developers
Classifier: License :: OSI Approved :: MIT License
Classifier: Natural Language :: English
Classifier: Operating System :: OS Independent
Classifier: Programming Language :: Python :: 2.7
Classifier: Programming Language :: Python :: 3.6
Classifier: Topic :: Documentation
Classifier: Topic :: Software Development :: Libraries :: Python Modules
Classifier: Topic :: System :: Installation/Setup
Classifier: Topic :: System :: Software Distribution
Requires-Dist: boto3
Requires-Dist: kafka
Requires-Dist: portalocker
Requires-Dist: psutil
Requires-Dist: setproctitle
